wgkits/__init__.py
wgkits/build_tool.py
wgkits/cn_conv.py
wgkits/excel_helper.py
wgkits/list_con.py
wgkits/overload.py
wgkits-0.1.2.6.dist-info/METADATA
wgkits-0.1.2.6.dist-info/RECORD
wgkits-0.1.2.6.dist-info/WHEEL
wgkits-0.1.2.6.dist-info/top_level.txt
