Metadata-Version: 2.1
Name: wgkits
Version: 0.1.2.6
Summary: Android build apk tools
Home-page: https://github.com/rontgen/wgkits
Author: rontgen
Author-email: rontgen@pku.edu.cn
License: UNKNOWN
Platform: UNKNOWN
Classifier: Programming Language :: Python :: 2
Classifier: License :: OSI Approved :: MIT License
Classifier: Operating System :: OS Independent
Requires-Dist: jinja2
Requires-Dist: backports.shutil-which
Requires-Dist: opencc-python-reimplemented
Requires-Dist: pandas
Requires-Dist: openpyxl
Requires-Dist: matplotlib
